CHANGELOG.txt
LICENCE.txt
MANIFEST.in
README.md
setup.py
MLChemTools/__init__.py
MLChemTools.egg-info/PKG-INFO
MLChemTools.egg-info/SOURCES.txt
MLChemTools.egg-info/dependency_links.txt
MLChemTools.egg-info/requires.txt
MLChemTools.egg-info/top_level.txt