Metadata-Version: 2.1
Name: MLChemTools
Version: 0.0.111
Summary: MLChemTools is a powerful Python package facilitating seamless integration of machine learning classifiers, regressors, and descriptor generators for efficient cheminformatics analysis.
Home-page: https://github.com/ahmed1212212/MLChemTools.git
Author: Ahmed Alhilal
Author-email: aalhilal@udel.edu
License: MIT
Keywords: Cheminformatics
Classifier: Development Status :: 5 - Production/Stable
Classifier: Intended Audience :: Education
Classifier: Operating System :: Microsoft :: Windows :: Windows 10
Classifier: License :: OSI Approved :: MIT License
Classifier: Programming Language :: Python :: 3
License-File: LICENCE.txt
